dlops/__init__.py
dlops/version.py
dlops-0.0.1.dist-info/LICENSE
dlops-0.0.1.dist-info/METADATA
dlops-0.0.1.dist-info/WHEEL
dlops-0.0.1.dist-info/top_level.txt
dlops-0.0.1.dist-info/RECORD
