Metadata-Version: 2.1
Name: dlops
Version: 0.0.1
Summary: DLOps: Deep Learning Development for Production
Home-page: http://dlops.io
Author: DLOps
Author-email: info@dlops.io
License: MIT
Project-URL: Source Code, https://github.com/dlops-io/dlops
Platform: UNKNOWN
Classifier: License :: OSI Approved :: MIT License
Classifier: Programming Language :: Python :: 3
Classifier: Programming Language :: Python :: 3.8
